agerch/__init__.py
agerch/core.py
agerch-0.0.1.dist-info/licenses/LICENSE
agerch-0.0.1.dist-info/METADATA
agerch-0.0.1.dist-info/WHEEL
agerch-0.0.1.dist-info/top_level.txt
agerch-0.0.1.dist-info/RECORD
